cmem_plugin_databus/__init__.py
cmem_plugin_databus/cmem_wrappers.py
cmem_plugin_databus/loader.py
cmem_plugin_databus/publisher.py
cmem_plugin_databus/utils.py
cmem_plugin_databus-1.0.1.dist-info/LICENSE
cmem_plugin_databus-1.0.1.dist-info/METADATA
cmem_plugin_databus-1.0.1.dist-info/WHEEL
cmem_plugin_databus-1.0.1.dist-info/RECORD
