Metadata-Version: 2.1
Name: cmem-plugin-databus
Version: 1.0.1
Summary: Load and publish datasets from a DBpedia databus service.
Home-page: https://github.com/dbpedia/cmem-plugin-databus
License: Apache-2.0
Keywords: eccenca Corporate Memory,plugin
Author: Denis Streitmatter
Author-email: streitmatter@informatik.uni-leipzig.de
Requires-Python: >=3.11,<4.0
Classifier: Development Status :: 4 - Beta
Classifier: Environment :: Plugins
Classifier: License :: OSI Approved :: Apache Software License
Classifier: Programming Language :: Python :: 3
Classifier: Programming Language :: Python :: 3.11
Classifier: Topic :: Software Development :: Libraries :: Python Modules
Requires-Dist: SPARQLWrapper (>=2.0.0,<3.0.0)
Requires-Dist: cmem-plugin-base (>=4.0.0,<5.0.0)
Requires-Dist: databusclient (==0.8)
